wikiget/__init__.py
wikiget/client.py
wikiget/dl.py
wikiget/exceptions.py
wikiget/file.py
wikiget/logging.py
wikiget/parse.py
wikiget/validations.py
wikiget/version.py
wikiget/wikiget.py
wikiget-0.8.0.data/data/share/doc/wikiget/LICENSE
wikiget-0.8.0.data/data/share/doc/wikiget/README.md
wikiget-0.8.0.data/data/share/man/man1/wikiget.1
wikiget-0.8.0.dist-info/METADATA
wikiget-0.8.0.dist-info/WHEEL
wikiget-0.8.0.dist-info/entry_points.txt
wikiget-0.8.0.dist-info/licenses/LICENSE
wikiget-0.8.0.dist-info/RECORD
