Metadata-Version: 2.1
Name: wikiget
Version: 0.8.0
Summary: CLI tool for downloading files from MediaWiki sites
Project-URL: Repository, https://github.com/clpo13/wikiget
Project-URL: Bug Reports, https://github.com/clpo13/wikiget/issues
Author-email: Cody Logan <cody@lokken.dev>
License: GPL-3.0-or-later
License-File: LICENSE
Keywords: commons,mediawiki,wikimedia,wikipedia
Classifier: Development Status :: 4 - Beta
Classifier: Environment :: Console
Classifier: Intended Audience :: End Users/Desktop
Classifier: License :: OSI Approved :: GNU General Public License v3 or later (GPLv3+)
Classifier: Operating System :: OS Independent
Classifier: Programming Language :: Python
Classifier: Programming Language :: Python :: 3
Classifier: Programming Language :: Python :: 3 :: Only
Classifier: Programming Language :: Python :: 3.7
Classifier: Programming Language :: Python :: 3.8
Classifier: Programming Language :: Python :: 3.9
Classifier: Programming Language :: Python :: 3.10
Classifier: Programming Language :: Python :: 3.11
Classifier: Programming Language :: Python :: 3.12
Classifier: Topic :: Internet
Classifier: Topic :: Internet :: WWW/HTTP
Classifier: Topic :: System :: Networking
Classifier: Topic :: Utilities
Requires-Python: >=3.7
Requires-Dist: mwclient>=0.10.0
Requires-Dist: requests
Requires-Dist: tqdm
